{
	"backtraceGraph" : 
	{
		"commands" : 
		[
			"_install",
			"install"
		],
		"files" : 
		[
			"/opt/ros/noetic/share/catkin/cmake/custom_install.cmake",
			"robot_model/CMakeLists.txt"
		],
		"nodes" : 
		[
			{
				"file" : 1
			},
			{
				"command" : 1,
				"file" : 1,
				"line" : 25,
				"parent" : 0
			},
			{
				"command" : 0,
				"file" : 0,
				"line" : 13,
				"parent" : 1
			},
			{
				"command" : 1,
				"file" : 1,
				"line" : 29,
				"parent" : 0
			},
			{
				"command" : 0,
				"file" : 0,
				"line" : 13,
				"parent" : 3
			}
		]
	},
	"installers" : 
	[
		{
			"backtrace" : 2,
			"component" : "Unspecified",
			"destination" : "lib",
			"paths" : 
			[
				"devel/lib/libmoveit_robot_model.so.1.1.9"
			],
			"targetId" : "moveit_robot_model::@66aef2cb65e23b1bc8dd",
			"targetIndex" : 76,
			"targetInstallNamelink" : "skip",
			"type" : "target"
		},
		{
			"backtrace" : 2,
			"component" : "Unspecified",
			"destination" : "lib",
			"paths" : 
			[
				"devel/lib/libmoveit_robot_model.so"
			],
			"targetId" : "moveit_robot_model::@66aef2cb65e23b1bc8dd",
			"targetIndex" : 76,
			"targetInstallNamelink" : "only",
			"type" : "target"
		},
		{
			"backtrace" : 4,
			"component" : "Unspecified",
			"destination" : "include",
			"paths" : 
			[
				{
					"from" : "robot_model/include",
					"to" : "."
				}
			],
			"type" : "directory"
		}
	],
	"paths" : 
	{
		"build" : "robot_model",
		"source" : "robot_model"
	}
}
